sqlalchemy_kusto/__init__.py
sqlalchemy_kusto/dbapi.py
sqlalchemy_kusto/dialect_base.py
sqlalchemy_kusto/dialect_kql.py
sqlalchemy_kusto/dialect_sql.py
sqlalchemy_kusto/errors.py
sqlalchemy_kusto-3.1.1.dist-info/licenses/LICENSE
sqlalchemy_kusto-3.1.1.dist-info/METADATA
sqlalchemy_kusto-3.1.1.dist-info/WHEEL
sqlalchemy_kusto-3.1.1.dist-info/entry_points.txt
sqlalchemy_kusto-3.1.1.dist-info/top_level.txt
sqlalchemy_kusto-3.1.1.dist-info/RECORD
