Metadata-Version: 2.4
Name: sqlalchemy-kusto
Version: 3.1.1
Summary: Azure Data Explorer (Kusto) dialect for SQLAlchemy
Home-page: https://github.com/dodopizza/sqlalchemy-kusto
Author: Dodo Engineering
Author-email: devcommunity@dodopizza.com
License: Apache License, Version 2.0
Project-URL: Bug Tracker, https://github.com/dodopizza/sqlalchemy-kusto/issues
Classifier: Intended Audience :: Developers
Classifier: Programming Language :: Python :: 3
Classifier: License :: OSI Approved :: Apache Software License
Requires-Python: >=3.10
License-File: LICENSE
Requires-Dist: azure-kusto-data==4.*
Requires-Dist: sqlalchemy==1.4.*
Requires-Dist: typing-extensions>=3.10
Provides-Extra: dev
Requires-Dist: black>=24.8.0; extra == "dev"
Requires-Dist: mypy>=1.14.1; extra == "dev"
Requires-Dist: pytest>=8.3.4; extra == "dev"
Requires-Dist: python-dotenv>=1.0.1; extra == "dev"
Requires-Dist: ruff>=0.9.3; extra == "dev"
Dynamic: author
Dynamic: author-email
Dynamic: classifier
Dynamic: description
Dynamic: description-content-type
Dynamic: home-page
Dynamic: license
Dynamic: license-file
Dynamic: project-url
Dynamic: provides-extra
Dynamic: requires-dist
Dynamic: requires-python
Dynamic: summary
